adafruit_pca9685.py
adafruit_circuitpython_pca9685-3.4.12.dist-info/LICENSE
adafruit_circuitpython_pca9685-3.4.12.dist-info/METADATA
adafruit_circuitpython_pca9685-3.4.12.dist-info/WHEEL
adafruit_circuitpython_pca9685-3.4.12.dist-info/top_level.txt
adafruit_circuitpython_pca9685-3.4.12.dist-info/RECORD
